{"file":"src/Controller/Seguranca/SegurancaConfigController.php","part":1,"eps":[{"operationId":"seguranca_ip_listar","method":"GET","path":"/api/seguranca/ip","fn":"ipListar"},{"operationId":"seguranca_ip_criar","method":"POST","path":"/api/seguranca/ip","fn":"ipCriar"},{"operationId":"seguranca_ip_editar","method":"PUT","path":"/api/seguranca/ip/{id}","fn":"ipEditar"},{"operationId":"seguranca_ip_editar","method":"PATCH","path":"/api/seguranca/ip/{id}","fn":"ipEditar"},{"operationId":"seguranca_ip_deletar","method":"DELETE","path":"/api/seguranca/ip/{id}","fn":"ipDeletar"},{"operationId":"seguranca_horario_listar","method":"GET","path":"/api/seguranca/horario","fn":"horarioListar"},{"operationId":"seguranca_horario_criar","method":"POST","path":"/api/seguranca/horario","fn":"horarioCriar"},{"operationId":"seguranca_horario_editar","method":"PUT","path":"/api/seguranca/horario/{id}","fn":"horarioEditar"}]}