{"file":"src/Controller/Bem/PropostaController.php","part":1,"eps":[{"operationId":"proposta_show","method":"GET","path":"/api/bem/propostas/{id}","fn":"showProposta"},{"operationId":"proposta_delete","method":"DELETE","path":"/api/bem/propostas/{id}","fn":"deletarProposta"},{"operationId":"proposta_list","method":"GET","path":"/api/bem/propostas","fn":"listProposta"},{"operationId":"proposta_docFormalizacao","method":"GET","path":"/api/bem/propostas/{id}/docFormalizacao","fn":"docFormalizacao"},{"operationId":"proposta_docFormalizacao","method":"POST","path":"/api/bem/propostas/{id}/docFormalizacao","fn":"docFormalizacao"},{"operationId":"propostas_public_list","method":"GET","path":"/api/public/service/bem/{id}/propostas","fn":"publicPropostas"},{"operationId":"bem_proposta_public_create","method":"POST","path":"/api/public/arrematantes/service/bem/{id}/enviar-proposta","fn":"registrarProposta"},{"operationId":"bem_proposta_create","method":"POST","path":"/api/bem/{id}/propostas","fn":"registrarProposta"}]}