{
  "updater_user_atualizacaoCadastral": {
    "summary": "Atualizar cadastro do usuário",
    "description": "Atualiza os dados cadastrais básicos do usuário informado (nome, CPF, e-mail e telefone celular). Todos os campos são obrigatórios e o CPF é validado pelo dígito verificador; documento inválido retorna erro. Cria o e-mail e o telefone padrão da pessoa caso ainda não existam e atualiza os valores existentes. Retorna os dados enviados com status 201.",
    "parameters": [
      {
        "name": "id",
        "in": "path",
        "required": true,
        "schema": { "type": "integer" },
        "description": "ID do usuário a ser atualizado."
      }
    ],
    "requestBody": {
      "required": true,
      "content": {
        "application/json": {
          "schema": {
            "type": "object",
            "required": ["name", "document", "email", "phoneNumber"],
            "properties": {
              "name": { "type": "string", "description": "Nome completo do usuário." },
              "document": { "type": "string", "description": "CPF do usuário (validado pelo dígito verificador; aceita com ou sem máscara)." },
              "email": { "type": "string", "format": "email", "description": "E-mail do usuário (vira o e-mail padrão da pessoa)." },
              "phoneNumber": { "type": "string", "description": "Telefone celular (apenas dígitos são gravados)." }
            }
          }
        }
      }
    }
  },
  "updater_user_aceitarTermos": {
    "summary": "Aceitar termos de uso",
    "description": "Registra o aceite do usuário autenticado aos Termos de Uso e à Política de Atendimento da Suporte Leilões. Gera um PDF de comprovação com os dados de identificação (nome, CPF, IP, navegador, ERP, carimbo de data/hora), opcionalmente aplica carimbo do tempo via Serpro/ICP-Brasil, envia o comprovante por e-mail ao usuário, ao jurídico e aos administradores configurados, grava a versão dos termos no config do usuário e persiste o registro de aceite no banco. Não recebe parâmetros obrigatórios no corpo. Retorna o conteúdo do termo aceito com status 201.",
    "parameters": []
  }
}
