{
  "tipoApreensao_create": {
    "summary": "Criar tipo de apreensão",
    "description": "Cria um novo tipo de apreensão de bem (ex.: classificação usada na origem/situação do bem apreendido). Valida os dados via formulário e persiste o registro. Retorna o tipo de apreensão criado com status 201.",
    "requestBody": {
      "required": true,
      "content": {
        "application/json": {
          "schema": {
            "type": "object",
            "properties": {
              "nome": {
                "type": "string",
                "description": "Nome do tipo de apreensão."
              },
              "active": {
                "type": "boolean",
                "description": "Indica se o tipo está ativo."
              }
            }
          }
        }
      }
    }
  },
  "tipoApreensao_list": {
    "summary": "Listar tipos de apreensão",
    "description": "Lista os tipos de apreensão de bens com paginação, ordenação e filtros. Suporta busca textual e filtro por status ativo/inativo. Retorna a coleção serializada (representação 'admin') junto com metadados de total e paginação.",
    "parameters": [
      {
        "name": "page",
        "in": "query",
        "required": false,
        "schema": {"type": "integer", "default": 1},
        "description": "Página atual (base 1)."
      },
      {
        "name": "limit",
        "in": "query",
        "required": false,
        "schema": {"type": "integer", "default": 100},
        "description": "Quantidade de registros por página (limitada pelo máximo permitido pelo servidor)."
      },
      {
        "name": "sortBy",
        "in": "query",
        "required": false,
        "schema": {"type": "string"},
        "description": "Campo usado para ordenar os resultados."
      },
      {
        "name": "descending",
        "in": "query",
        "required": false,
        "schema": {"type": "boolean"},
        "description": "Se verdadeiro, ordena de forma decrescente."
      },
      {
        "name": "search",
        "in": "query",
        "required": false,
        "schema": {"type": "string"},
        "description": "Termo de busca textual aplicado aos tipos de apreensão."
      },
      {
        "name": "active",
        "in": "query",
        "required": false,
        "schema": {"type": "string"},
        "description": "Filtra por status: '1' para ativos e '0' para inativos."
      }
    ]
  },
  "tipoApreensao_show": {
    "summary": "Exibir tipo de apreensão",
    "description": "Retorna os dados de um tipo de apreensão específico identificado pelo ID, na representação 'admin'.",
    "parameters": [
      {
        "name": "id",
        "in": "path",
        "required": true,
        "schema": {"type": "integer"},
        "description": "ID do tipo de apreensão."
      }
    ]
  },
  "tipoApreensao_update": {
    "summary": "Atualizar tipo de apreensão",
    "description": "Atualiza um tipo de apreensão existente identificado pelo ID. Aceita PUT (substituição) e PATCH (atualização parcial), validando os dados via formulário. Retorna o registro atualizado.",
    "parameters": [
      {
        "name": "id",
        "in": "path",
        "required": true,
        "schema": {"type": "integer"},
        "description": "ID do tipo de apreensão."
      }
    ],
    "requestBody": {
      "required": true,
      "content": {
        "application/json": {
          "schema": {
            "type": "object",
            "properties": {
              "nome": {
                "type": "string",
                "description": "Nome do tipo de apreensão."
              },
              "active": {
                "type": "boolean",
                "description": "Indica se o tipo está ativo."
              }
            }
          }
        }
      }
    }
  },
  "tipoApreensao_delete": {
    "summary": "Excluir tipo de apreensão",
    "description": "Exclui logicamente (soft delete) um tipo de apreensão identificado pelo ID, marcando-o como removido sem apagar fisicamente o registro. Retorna o registro afetado.",
    "parameters": [
      {
        "name": "id",
        "in": "path",
        "required": true,
        "schema": {"type": "integer"},
        "description": "ID do tipo de apreensão."
      }
    ]
  }
}
